src/Core.py
src/DataClasses.py
src/Widgets.py
src/Workers.py
src/__init__.py
src/curves.py
src/main.py
src/tooltips.py
src/utils.py
laser_level_webcam-1.0.0.dist-info/LICENSE
laser_level_webcam-1.0.0.dist-info/METADATA
laser_level_webcam-1.0.0.dist-info/WHEEL
laser_level_webcam-1.0.0.dist-info/entry_points.txt
laser_level_webcam-1.0.0.dist-info/top_level.txt
laser_level_webcam-1.0.0.dist-info/RECORD
