Metadata-Version: 2.1
Name: laser-level-webcam
Version: 1.0.0
Summary: A tool for measuring height changes using a laser level and a webcam.
Home-page: https://github.com/bhowiebkr/laser-level-webcam
Author: Bryan Howard
Author-email: bhowiebkr@gmail.com
License: MIT
Classifier: License :: OSI Approved :: GNU Affero General Public License v3
Classifier: License :: OSI Approved :: MIT License
Requires-Python: !=3.10.*
License-File: LICENSE
Requires-Dist: PySide6
Requires-Dist: matplotlib
Requires-Dist: numpy
Requires-Dist: pyqtdarktheme
Requires-Dist: qimage2ndarray
Requires-Dist: scipy
